RobotFrameworkResultAnalyzer/__init__.py
RobotFrameworkResultAnalyzer/listener.py
robotframeworkresultanalyzer-1.0.0.dist-info/METADATA
robotframeworkresultanalyzer-1.0.0.dist-info/WHEEL
robotframeworkresultanalyzer-1.0.0.dist-info/entry_points.txt
robotframeworkresultanalyzer-1.0.0.dist-info/licenses/LICENSE
robotframeworkresultanalyzer-1.0.0.dist-info/RECORD
