Metadata-Version: 2.1
Name: RobotFrameworkResultAnalyzer
Version: 1.0.0
Summary: Robot Framework listener to generate understandable output of test results
Author-Email: Joonas Jauhiainen <joonas.jauhiainen@gmail.com>
License: The GNU General Public License v3.0
Requires-Python: >=3.9
Requires-Dist: robotframework==7.1.1
